annoy/__init__.py
annoy/__init__.pyi
annoy/annoylib.cp312-win_amd64.pyd
annoy/py.typed
annoy_binary-1.17.3.dist-info/LICENSE
annoy_binary-1.17.3.dist-info/METADATA
annoy_binary-1.17.3.dist-info/WHEEL
annoy_binary-1.17.3.dist-info/top_level.txt
annoy_binary-1.17.3.dist-info/RECORD
