Metadata-Version: 2.1
Name: annoy-binary
Version: 1.17.3
Summary: Approximate Nearest Neighbors in C++/Python optimized for memory usage and loading/saving to disk. Prebuilt binary
Home-page: https://github.com/spotify/annoy
Author: Erik Bernhardsson
Author-email: mail@erikbern.com
License: Apache License 2.0
Keywords: nns,approximate nearest neighbor search
Classifier: Development Status :: 5 - Production/Stable
Classifier: Programming Language :: Python
Classifier: Programming Language :: Python :: 3.12
License-File: LICENSE
